lemuras/__init__.py
lemuras/column.py
lemuras/grouped.py
lemuras/processing.py
lemuras/row.py
lemuras/table.py
lemuras/utils.py
tests/__init__.py
tests/sample_data.py
tests/test_column.py
tests/test_format_csv.py
tests/test_format_html.py
tests/test_format_json.py
tests/test_format_sql.py
tests/test_row.py
tests/test_table.py
tests/test_table_concat.py
tests/test_table_groupby.py
tests/test_table_merge.py
tests/test_table_pivot.py
Lemuras-1.2.3.dist-info/LICENSE
Lemuras-1.2.3.dist-info/METADATA
Lemuras-1.2.3.dist-info/WHEEL
Lemuras-1.2.3.dist-info/top_level.txt
Lemuras-1.2.3.dist-info/RECORD
