Metadata-Version: 2.1
Name: Lemuras
Version: 1.2.3
Summary: A small Python library to deal with big tables
Home-page: https://github.com/AivanF/Lemuras
Author: AivanF.
Author-email: projects@aivanf.com
License: UNKNOWN
Platform: UNKNOWN
Classifier: Development Status :: 5 - Production/Stable
Classifier: Programming Language :: Python :: 2
Classifier: Programming Language :: Python :: 3
Classifier: Operating System :: OS Independent
Classifier: Environment :: Console
Classifier: Topic :: Utilities
Classifier: Topic :: Text Processing
Classifier: Topic :: Scientific/Engineering :: Information Analysis
Classifier: License :: Freely Distributable
